django_finance_12bucks-0.1.0.dist-info/licenses/LICENSE
migrations/0001_initial.py
migrations/0002_miles.py
migrations/0003_mileagerate.py
migrations/0004_alter_transaction_receipt.py
migrations/0005_remove_invoiceitem_invoice_numb_invoiceitem_invoice_and_more.py
migrations/0006_alter_invoice_options_alter_invoiceitem_invoice_and_more.py
migrations/__init__.py
django_finance_12bucks-0.1.0.dist-info/METADATA
django_finance_12bucks-0.1.0.dist-info/WHEEL
django_finance_12bucks-0.1.0.dist-info/top_level.txt
django_finance_12bucks-0.1.0.dist-info/RECORD
