Metadata-Version: 2.4
Name: django-finance-12bucks
Version: 0.1.0
Summary: A Django finance app to track income, expenses, mileage, and generate reports.
Home-page: https://github.com/yourusername/12bucks
Author: Tom Stout
Author-email: tom@airborne-images.net
License: MIT
Classifier: Framework :: Django
Classifier: Programming Language :: Python :: 3
Classifier: License :: OSI Approved :: MIT License
Classifier: Operating System :: OS Independent
License-File: LICENSE
Requires-Dist: Django>=4.0
Requires-Dist: psycopg2-binary
Requires-Dist: pillow
Requires-Dist: django-crispy-forms
Requires-Dist: django-bootstrap-v5
Requires-Dist: django-environ
Requires-Dist: weasyprint
Dynamic: author
Dynamic: author-email
Dynamic: classifier
Dynamic: description
Dynamic: description-content-type
Dynamic: home-page
Dynamic: license
Dynamic: license-file
Dynamic: requires-dist
Dynamic: summary
